UncertainSCI/__init__.py
UncertainSCI/distributions.py
UncertainSCI/families.py
UncertainSCI/indexing.py
UncertainSCI/model_examples.py
UncertainSCI/opoly1d.py
UncertainSCI/opolynd.py
UncertainSCI/pce.py
UncertainSCI/sampling.py
UncertainSCI/transformations.py
UncertainSCI/ttr.py
UncertainSCI/vis.py
UncertainSCI/utils/__init__.py
UncertainSCI/utils/array_unique.py
UncertainSCI/utils/casting.py
UncertainSCI/utils/compute_moment.py
UncertainSCI/utils/linalg.py
UncertainSCI/utils/prob.py
UncertainSCI/utils/quad.py
UncertainSCI/utils/verify_orthonormal.py
UncertainSCI/utils/version.py
UncertainSCI-1.0.1.1.dist-info/LICENSE
UncertainSCI-1.0.1.1.dist-info/METADATA
UncertainSCI-1.0.1.1.dist-info/WHEEL
UncertainSCI-1.0.1.1.dist-info/top_level.txt
UncertainSCI-1.0.1.1.dist-info/RECORD
