Metadata-Version: 2.1
Name: UncertainSCI
Version: 1.0.1.1
Summary: A Non-invasive Uncertainty Quantification tool
Home-page: https://sci.utah.edu/sci-software/simulation/uncertainsci.html
Download-URL: https://github.com/SCIInstitute/UncertainSCI
Author: UncertainSCI Developers
Author-email: uncertainsci@sci.utah.edu
License: MIT
Keywords: Uncertainty Quantification,Simulation
Classifier: License :: OSI Approved :: MIT License
Classifier: Programming Language :: Python :: 3
Classifier: Programming Language :: Python :: 3.9
Classifier: Programming Language :: Python :: 3.10
Classifier: Programming Language :: Python :: 3.11
Classifier: Development Status :: 4 - Beta
Classifier: Intended Audience :: Developers
Classifier: Intended Audience :: Education
Classifier: Intended Audience :: Healthcare Industry
Classifier: Intended Audience :: Science/Research
Classifier: Topic :: Scientific/Engineering
Classifier: Topic :: Scientific/Engineering :: Medical Science Apps.
Classifier: Topic :: Scientific/Engineering :: Information Analysis
Classifier: Topic :: Software Development :: Libraries
Classifier: Operating System :: Android
Classifier: Operating System :: Microsoft :: Windows
Classifier: Operating System :: POSIX
Classifier: Operating System :: Unix
Classifier: Operating System :: MacOS
License-File: LICENSE
Requires-Dist: matplotlib >=3.1.3
Requires-Dist: numpy >=1.22
Requires-Dist: scipy >=1.4.1
